AUTHORS
ChangeLog
LICENSE
MANIFEST.in
README.rst
requirements.txt
setup.cfg
setup.py
test-requirements.txt
tox.ini
rpm_vercmp/__init__.py
rpm_vercmp/vercmp.py
rpm_vercmp.egg-info/PKG-INFO
rpm_vercmp.egg-info/SOURCES.txt
rpm_vercmp.egg-info/dependency_links.txt
rpm_vercmp.egg-info/not-zip-safe
rpm_vercmp.egg-info/pbr.json
rpm_vercmp.egg-info/top_level.txt
rpm_vercmp/tests/__init__.py
rpm_vercmp/tests/vercmp_test.py